chili_pepper/__init__.py
chili_pepper/app.py
chili_pepper/config.py
chili_pepper/deployer.py
chili_pepper/exception.py
chili_pepper/main.py
tests/__init__.py
tests/unit/__init__.py
tests/unit/conftest.py
tests/unit/test_app.py
tests/unit/test_deployer.py
chili_pepper-0.0.3.dist-info/METADATA
chili_pepper-0.0.3.dist-info/WHEEL
chili_pepper-0.0.3.dist-info/entry_points.txt
chili_pepper-0.0.3.dist-info/top_level.txt
chili_pepper-0.0.3.dist-info/RECORD
